camel_morph/VERSION
camel_morph/__init__.py
camel_morph/db_maker.py
camel_morph/db_maker_utils.py
camel_morph/camel_tools/__init__.py
camel_morph/camel_tools/setup.py
camel_morph/camel_tools/camel_tools/cli/__init__.py
camel_morph/camel_tools/camel_tools/cli/camel_arclean.py
camel_morph/camel_tools/camel_tools/cli/camel_data.py
camel_morph/camel_tools/camel_tools/cli/camel_dediac.py
camel_morph/camel_tools/camel_tools/cli/camel_diac.py
camel_morph/camel_tools/camel_tools/cli/camel_morphology.py
camel_morph/camel_tools/camel_tools/cli/camel_transliterate.py
camel_morph/camel_tools/camel_tools/cli/camel_word_tokenize.py
camel_morph/camel_tools/camel_tools/cli/utils.py
camel_morph/camel_tools/camel_tools/data/__init__.py
camel_morph/camel_tools/camel_tools/data/catalogue.py
camel_morph/camel_tools/camel_tools/data/downloader.py
camel_morph/camel_tools/camel_tools/disambig/__init__.py
camel_morph/camel_tools/camel_tools/disambig/common.py
camel_morph/camel_tools/camel_tools/disambig/mle.py
camel_morph/camel_tools/camel_tools/disambig/score_function.py
camel_morph/camel_tools/camel_tools/morphology/__init__.py
camel_morph/camel_tools/camel_tools/morphology/analyzer.py
camel_morph/camel_tools/camel_tools/morphology/database.py
camel_morph/camel_tools/camel_tools/morphology/errors.py
camel_morph/camel_tools/camel_tools/morphology/generator.py
camel_morph/camel_tools/camel_tools/morphology/reinflector.py
camel_morph/camel_tools/camel_tools/morphology/utils.py
camel_morph/camel_tools/camel_tools/tokenizers/__init__.py
camel_morph/camel_tools/camel_tools/tokenizers/morphological.py
camel_morph/camel_tools/camel_tools/tokenizers/word.py
camel_morph/camel_tools/camel_tools/utils/__init__.py
camel_morph/camel_tools/camel_tools/utils/charmap.py
camel_morph/camel_tools/camel_tools/utils/charsets.py
camel_morph/camel_tools/camel_tools/utils/dediac.py
camel_morph/camel_tools/camel_tools/utils/normalize.py
camel_morph/camel_tools/camel_tools/utils/stringutils.py
camel_morph-0.9.2.dist-info/LICENSE
camel_morph-0.9.2.dist-info/METADATA
camel_morph-0.9.2.dist-info/WHEEL
camel_morph-0.9.2.dist-info/top_level.txt
camel_morph-0.9.2.dist-info/RECORD
