Metadata-Version: 2.1
Name: camel-morph
Version: 0.9.2
Summary: An environment for creating, and debugging morphological grammars that can be used in conjunction with morphological analyzers/generatorsdeveloped by the CAMeL Lab at New York University Abu Dhabi.
Home-page: https://github.com/CAMeL-Lab/camel_morph
Author: Christian Khairallah
Author-email: christian.khairallah@nyu.edu
Maintainer: Christian Khairallah
Maintainer-email: christian.khairallah@nyu.edu
License: MIT
Classifier: Development Status :: 5 - Production/Stable
Classifier: Environment :: Console
Classifier: Intended Audience :: Developers
Classifier: Intended Audience :: Education
Classifier: Intended Audience :: Information Technology
Classifier: Intended Audience :: Science/Research
Classifier: License :: OSI Approved :: MIT License
Classifier: Natural Language :: Arabic
Classifier: Topic :: Text Processing
Classifier: Topic :: Text Processing :: Linguistic
Requires-Python: >=3.8, <3.10
License-File: LICENSE
Requires-Dist: flask
Requires-Dist: gspread (==5.1.1)
Requires-Dist: numpy
Requires-Dist: pandas
Requires-Dist: tqdm
Requires-Dist: pyrsistent
Requires-Dist: emoji
